[
  {
    "$type": "FurnitureStoreFront.Models.Cart.Receipt, FurnitureStoreFront",
    "Date": "20/01/2019 22:53:33",
    "FinalPrice": 6798.0,
    "FullName": "Kaiser Sousei",
    "AccountNr": "***********3138"
  },
  {
    "$type": "FurnitureStoreFront.Models.Cart.Receipt, FurnitureStoreFront",
    "Date": "21/01/2019 10:44:07",
    "FinalPrice": 768.0,
    "FullName": "Kaiser Sousei",
    "AccountNr": "***********3138"
  },
  {
    "$type": "FurnitureStoreFront.Models.Cart.Receipt, FurnitureStoreFront",
    "Date": "22/01/2019 10:36:10",
    "FinalPrice": 7566.0,
    "FullName": "Kaiser Sousei",
    "AccountNr": "***********3138"
  },
  {
    "$type": "FurnitureStoreFront.Models.Cart.Receipt, FurnitureStoreFront",
    "Date": "22/01/2019 12:11:27",
    "FinalPrice": 597.0,
    "FullName": "Maria Sousei",
    "AccountNr": "***********3235"
  }
]